{
 "missionId": "725/a",
 "missionName": "Refinery Explosion (Major)",
 "requirements": [
  {
   "requirement": "firetrucks",
   "qty": "30"
  },
  {
   "requirement": "platform trucks",
   "qty": "10"
  },
  {
   "requirement": "heavy rescue vehicles",
   "qty": "10"
  },
  {
   "requirement": "hazmat vehicles",
   "qty": "6"
  },
  {
   "requirement": "battalion chief vehicles",
   "qty": "7"
  },
  {
   "requirement": "mobile command vehicles",
   "qty": "2"
  },
  {
   "requirement": "mobile air vehicles",
   "qty": "5"
  },
  {
   "requirement": "foam tenders",
   "qty": "5"
  },
  {
   "requirement": "water tankers",
   "qty": "5"
  },
  {
   "requirement": "police cars",
   "qty": "10"
  },
  {
   "requirement": "sheriffs",
   "qty": "4"
  },
  {
   "requirement": "fbi units",
   "qty": "4"
  },
  {
   "requirement": "fbi investigation wagons",
   "qty": "1"
  },
  {
   "requirement": "fire investigation units",
   "qty": "6"
  },
  {
   "requirement": "max. patients",
   "qty": "50"
  }
 ],
 "credits": "42500",
 "version": "86758045589765406153361761718276001309"
}