{"missionId": "34/a", "missionName": "Feu d'ERP - Hôpital", "requirements": [{"requirement": "extensions de soutien à incendie s", "qty": "3"}, {"requirement": "fourgons d’incendie", "qty": "10"}, {"requirement": "chefs de groupe ou vlhr", "qty": "2"}, {"requirement": "camions-citernes", "qty": "1"}, {"requirement": "moyen elévateur aérien", "qty": "3"}, {"requirement": "camions dévidoirs s", "qty": "3"}, {"requirement": "motopompes s", "qty": "2"}, {"requirement": "max. patients", "qty": "25"}], "credits": "6300"}