{
 "missionId": "41/a",
 "missionName": "Feu d'ERP - Concessionnaire",
 "requirements": [
  {
   "requirement": "fourgons d’incendie",
   "qty": "8"
  },
  {
   "requirement": "vlhr",
   "qty": "2"
  },
  {
   "requirement": "moyen elévateur aérien",
   "qty": "2"
  },
  {
   "requirement": "véhicule de secours routier",
   "qty": "1"
  },
  {
   "requirement": "voitures de police es",
   "qty": "2"
  },
  {
   "requirement": "fmogp",
   "qty": "2"
  },
  {
   "requirement": "motopompes",
   "qty": "2"
  },
  {
   "requirement": "max. patients",
   "qty": "4"
  }
 ],
 "credits": "7100",
 "version": "51756080996354020811152851874928945415"
}