{
 "missionId": "460",
 "missionName": "Wypadek z udziałem cysterny przewożącej niebezpieczną substancję",
 "requirements": [
  {
   "requirement": "samochody pożarnicze",
   "qty": "6"
  },
  {
   "requirement": "slop lub slrr",
   "qty": "2"
  },
  {
   "requirement": "samochody ratownictwa technicznego",
   "qty": "3"
  },
  {
   "requirement": "samochody spgaz",
   "qty": "1"
  },
  {
   "requirement": "sp rchem",
   "qty": "2"
  },
  {
   "requirement": "radiowozy",
   "qty": "3"
  },
  {
   "requirement": "maks. pacjenci",
   "qty": "2"
  }
 ],
 "credits": "11000",
 "version": "287710100653298666478684047024245464232"
}