{
 "missionId": "244",
 "missionName": "Pessoa debaixo do trem",
 "requirements": [
  {
   "requirement": "caminhões de bombeiro necessários",
   "qty": "4"
  },
  {
   "requirement": "viaturas de batalhão necessárias",
   "qty": "4"
  },
  {
   "requirement": "veículos de resgate pesado necessários",
   "qty": "2"
  },
  {
   "requirement": "viaturas de polícia necessárias",
   "qty": "5"
  },
  {
   "requirement": "máx. de pacientes",
   "qty": "1"
  },
  {
   "requirement": "probabilidade de serem necessários cuidados criticos",
   "qty": "100"
  }
 ],
 "credits": "7000",
 "version": "177279031718983697908422368632374065741"
}