{
 "missionId": "72/b",
 "missionName": "Light Aircraft Crash",
 "requirements": [
  {
   "requirement": "fire engines",
   "qty": "4"
  },
  {
   "requirement": "fire officers",
   "qty": "1"
  },
  {
   "requirement": "rescue support vehicles",
   "qty": "1"
  },
  {
   "requirement": "water carriers",
   "qty": "1"
  },
  {
   "requirement": "hazmat units or cbrn vehicles",
   "qty": "1"
  },
  {
   "requirement": "foam units",
   "qty": "2"
  },
  {
   "requirement": "max. patients",
   "qty": "4"
  }
 ],
 "credits": "4800",
 "version": "104023369430201794181132675167751451020"
}